flashforge/__init__.py
flashforge/client.py
flashforge/api/__init__.py
flashforge/api/constants/__init__.py
flashforge/api/constants/commands.py
flashforge/api/constants/endpoints.py
flashforge/api/controls/__init__.py
flashforge/api/controls/control.py
flashforge/api/controls/files.py
flashforge/api/controls/info.py
flashforge/api/controls/job_control.py
flashforge/api/controls/temp_control.py
flashforge/api/filament/__init__.py
flashforge/api/filament/filament.py
flashforge/api/misc/__init__.py
flashforge/api/misc/scientific_notation.py
flashforge/api/misc/temperature.py
flashforge/api/network/__init__.py
flashforge/api/network/fnet_code.py
flashforge/api/network/utils.py
flashforge/discovery/__init__.py
flashforge/discovery/discovery.py
flashforge/models/__init__.py
flashforge/models/machine_info.py
flashforge/models/responses.py
flashforge/tcp/__init__.py
flashforge/tcp/ff_client.py
flashforge/tcp/tcp_client.py
flashforge/tcp/gcode/__init__.py
flashforge/tcp/gcode/gcode_controller.py
flashforge/tcp/gcode/gcodes.py
flashforge/tcp/parsers/__init__.py
flashforge/tcp/parsers/endstop_status.py
flashforge/tcp/parsers/location_info.py
flashforge/tcp/parsers/print_status.py
flashforge/tcp/parsers/printer_info.py
flashforge/tcp/parsers/temp_info.py
flashforge/tcp/parsers/thumbnail_info.py
flashforge_python_api-1.0.2.dist-info/METADATA
flashforge_python_api-1.0.2.dist-info/WHEEL
flashforge_python_api-1.0.2.dist-info/entry_points.txt
flashforge_python_api-1.0.2.dist-info/licenses/LICENSE
flashforge_python_api-1.0.2.dist-info/RECORD
