Metadata-Version: 2.4
Name: flashforge-python-api
Version: 1.0.2
Summary: A comprehensive Python library for controlling FlashForge 3D printers
Project-URL: Homepage, https://github.com/GhostTypes/ff-5mp-api-py
Project-URL: Documentation, https://github.com/GhostTypes/ff-5mp-api-py#readme
Project-URL: Repository, https://github.com/GhostTypes/ff-5mp-api-py.git
Project-URL: Issues, https://github.com/GhostTypes/ff-5mp-api-py/issues
Author-email: GhostTypes <notghosttypes@gmail.com>
License-Expression: MIT
License-File: LICENSE
Keywords: 3d-printer,api,async,control,flashforge,python
Classifier: Development Status :: 5 - Production/Stable
Classifier: Intended Audience :: Developers
Classifier: Programming Language :: Python :: 3
Classifier: Programming Language :: Python :: 3.8
Classifier: Programming Language :: Python :: 3.9
Classifier: Programming Language :: Python :: 3.10
Classifier: Programming Language :: Python :: 3.11
Classifier: Programming Language :: Python :: 3.12
Classifier: Topic :: Scientific/Engineering
Classifier: Topic :: Software Development :: Libraries :: Python Modules
Classifier: Topic :: System :: Hardware :: Hardware Drivers
Requires-Python: >=3.8
Requires-Dist: aiohttp>=3.8.0
Requires-Dist: netifaces>=0.11.0
Requires-Dist: pydantic>=2.0.0
Requires-Dist: requests>=2.31.0
Provides-Extra: all
Requires-Dist: black>=23.0.0; extra == 'all'
Requires-Dist: mypy>=1.0.0; extra == 'all'
Requires-Dist: pillow>=10.0.0; extra == 'all'
Requires-Dist: pre-commit>=3.0.0; extra == 'all'
Requires-Dist: pytest-asyncio>=0.21.0; extra == 'all'
Requires-Dist: pytest-cov>=4.0.0; extra == 'all'
Requires-Dist: pytest>=7.0.0; extra == 'all'
Requires-Dist: ruff>=0.1.0; extra == 'all'
Provides-Extra: dev
Requires-Dist: black>=23.0.0; extra == 'dev'
Requires-Dist: mypy>=1.0.0; extra == 'dev'
Requires-Dist: pre-commit>=3.0.0; extra == 'dev'
Requires-Dist: pytest-asyncio>=0.21.0; extra == 'dev'
Requires-Dist: pytest-cov>=4.0.0; extra == 'dev'
Requires-Dist: pytest>=7.0.0; extra == 'dev'
Requires-Dist: ruff>=0.1.0; extra == 'dev'
Provides-Extra: imaging
Requires-Dist: pillow>=10.0.0; extra == 'imaging'
